Metadata-Version: 2.1
Name: min-dalle
Version: 0.2.29
Summary: min(DALL·E)
Home-page: https://github.com/kuprel/min-dalle
Author: Brett Kuprel
Author-email: brkuprel@gmail.com
License: MIT
Keywords: artificial intelligence,deep learning,text-to-image,pytorch
License-File: LICENSE
